README.md
pygpar.py
setup.py
pygpar.egg-info/PKG-INFO
pygpar.egg-info/SOURCES.txt
pygpar.egg-info/dependency_links.txt
pygpar.egg-info/top_level.txt