Metadata-Version: 1.0
Name: pygpar
Version: 1.0
Summary: A python wrapper around GNU parallel.
Home-page: https://github.com/zardus/pygpar
Author: UNKNOWN
Author-email: UNKNOWN
License: UNKNOWN
Platform: UNKNOWN
